Workbook
Name anos: Simulador!$D$7
Name aporte: Simulador!$D$6
Name dividendos: Simulador!$D$17
Name lista_perfis: Perfis!$H$5:$H$7
Name lista_tipos: Perfis!$F$5:$F$10
Name patrimonio: Simulador!$D$15
Name pct_aporte: Configurações!$C$8
Name perfil: Simulador!$D$9
Name salario: Configurações!$C$7
Name sugestao_aporte: Configurações!$C$9
Name tabela_perfis: Perfis!$A$5:$D$22
Name taxa_mensal: Simulador!$D$8

Sheet Simulador
C2: Simulador de Fundos Imobiliários
C4: Preencha as células amarelas. As células cinza são calculadas e não devem ser editadas.
C5: Seus dados
C6: Quanto investir por mês (R$) | D6: 1000 | E6: ="Sugestão ("&ROUND(pct_aporte*100,0)&"% do salário):" -> Sugestão (30% do salário): | G6: =sugestao_aporte -> 1500
C7: Por quantos anos | D7: 10 | E7: de 1 a 30 anos
C8: Taxa de rendimento mensal | D8: 0.008 | E8: ex.: 0,80% ao mês (hipótese de rendimento mensal de FIIs)
C9: Perfil do investidor | D9: Conservador | E9: escolha na lista
C11: Resultado
C12: Indicador | D12: Aporte informado | E12: 30% do salário
C13: Aporte mensal | D13: =aporte -> 1000 | E13: =sugestao_aporte -> 1500
C14: Total investido | D14: =D13*anos*12 -> 120000 | E14: =E13*anos*12 -> 180000
C15: Patrimônio acumulado | D15: =FV(taxa_mensal,anos*12,-D13) -> 200217.47 | E15: =FV(taxa_mensal,anos*12,-E13) -> 300326.2
C16: Rendimento acumulado | D16: =D15-D14 -> 80217.469 | E16: =E15-E14 -> 120326.2
C17: Dividendos por mês | D17: =D15*taxa_mensal -> 1601.7398 | E17: =E15*taxa_mensal -> 2402.6096
C19: Divisão do aporte por tipo de fundo
C20: Tipo de fundo | D20: % do aporte | E20: Aporte mensal (R$)
C21: =Perfis!F5 -> Papel (CRI) | D21: =VLOOKUP(perfil&"|"&C21,tabela_perfis,4,FALSE()) -> 0.4 | E21: =D21*aporte -> 400
C22: =Perfis!F6 -> Logística | D22: =VLOOKUP(perfil&"|"&C22,tabela_perfis,4,FALSE()) -> 0.2 | E22: =D22*aporte -> 200
C23: =Perfis!F7 -> Shoppings | D23: =VLOOKUP(perfil&"|"&C23,tabela_perfis,4,FALSE()) -> 0.1 | E23: =D23*aporte -> 100
C24: =Perfis!F8 -> Lajes corporativas | D24: =VLOOKUP(perfil&"|"&C24,tabela_perfis,4,FALSE()) -> 0.05 | E24: =D24*aporte -> 50
C25: =Perfis!F9 -> Fundos de fundos (FoF) | D25: =VLOOKUP(perfil&"|"&C25,tabela_perfis,4,FALSE()) -> 0.2 | E25: =D25*aporte -> 200
C26: =Perfis!F10 -> Híbridos e desenvolvimento | D26: =VLOOKUP(perfil&"|"&C26,tabela_perfis,4,FALSE()) -> 0.05 | E26: =D26*aporte -> 50
C27: Total | D27: =SUM(D21:D26) -> 1 | E27: =SUM(E21:E26) -> 1000
C30: Cenários de 2 a 30 anos
C31: Prazo (anos) | D31: Total investido | E31: Patrimônio | F31: Dividendos por mês | G31: Patrimônio (30% do salário) | H31: Dividendos por mês (30%)
C32: 2 | D32: =aporte*$C32*12 -> 24000 | E32: =FV(taxa_mensal,$C32*12,-aporte) -> 26343.155 | F32: =E32*taxa_mensal -> 210.74524 | G32: =FV(taxa_mensal,$C32*12,-sugestao_aporte) -> 39514.733 | H32: =G32*taxa_mensal -> 316.11786
C33: 5 | D33: =aporte*$C33*12 -> 60000 | E33: =FV(taxa_mensal,$C33*12,-aporte) -> 76623.867 | F33: =E33*taxa_mensal -> 612.99093 | G33: =FV(taxa_mensal,$C33*12,-sugestao_aporte) -> 114935.8 | H33: =G33*taxa_mensal -> 919.4864
C34: 10 | D34: =aporte*$C34*12 -> 120000 | E34: =FV(taxa_mensal,$C34*12,-aporte) -> 200217.47 | F34: =E34*taxa_mensal -> 1601.7398 | G34: =FV(taxa_mensal,$C34*12,-sugestao_aporte) -> 300326.2 | H34: =G34*taxa_mensal -> 2402.6096
C35: 20 | D35: =aporte*$C35*12 -> 240000 | E35: =FV(taxa_mensal,$C35*12,-aporte) -> 721131.22 | F35: =E35*taxa_mensal -> 5769.0498 | G35: =FV(taxa_mensal,$C35*12,-sugestao_aporte) -> 1081696.8 | H35: =G35*taxa_mensal -> 8653.5746
C36: 30 | D36: =aporte*$C36*12 -> 360000 | E36: =FV(taxa_mensal,$C36*12,-aporte) -> 2076413.2 | F36: =E36*taxa_mensal -> 16611.306 | G36: =FV(taxa_mensal,$C36*12,-sugestao_aporte) -> 3114619.8 | H36: =G36*taxa_mensal -> 24916.959
C38: Dividendos por mês = patrimônio × taxa de rendimento mensal (estimativa, com a taxa constante).
C39: Simulação com fins didáticos, com valores de exemplo. Não é recomendação de investimento.

Sheet Configurações
B2: Configurações
B4: Valores de exemplo. Células amarelas são editáveis; cinza é calculado.
B6: Item | C6: Valor | D6: Observação
B7: Salário mensal (exemplo) | C7: 5000 | D7: Valor fictício, troque pelo seu caso
B8: Percentual do salário para aportar | C8: 0.3 | D8: Regra de bolso de 30% do salário
B9: Sugestão de aporte mensal | C9: =salario*pct_aporte -> 1500 | D9: Calculado: salário × percentual

Sheet Perfis
A1: Tabela de apoio: perfil, tipo de fundo e percentual
A4: Chave | B4: Perfil | C4: Tipo de fundo | D4: Percentual | F4: Tipos de fundo | H4: Perfil | I4: Soma dos % | J4: Conferência
A5: =B5&"|"&C5 -> Conservador|Papel (CRI) | B5: Conservador | C5: Papel (CRI) | D5: 0.4 | F5: Papel (CRI) | H5: Conservador | I5: =SUMIF($B$5:$B$22,H5,$D$5:$D$22) -> 1 | J5: =IF(ROUND(I5,4)=1,"OK","Ajustar") -> OK
A6: =B6&"|"&C6 -> Conservador|Logística | B6: Conservador | C6: Logística | D6: 0.2 | F6: Logística | H6: Moderado | I6: =SUMIF($B$5:$B$22,H6,$D$5:$D$22) -> 1 | J6: =IF(ROUND(I6,4)=1,"OK","Ajustar") -> OK
A7: =B7&"|"&C7 -> Conservador|Shoppings | B7: Conservador | C7: Shoppings | D7: 0.1 | F7: Shoppings | H7: Arrojado | I7: =SUMIF($B$5:$B$22,H7,$D$5:$D$22) -> 1 | J7: =IF(ROUND(I7,4)=1,"OK","Ajustar") -> OK
A8: =B8&"|"&C8 -> Conservador|Lajes corporativas | B8: Conservador | C8: Lajes corporativas | D8: 0.05 | F8: Lajes corporativas
A9: =B9&"|"&C9 -> Conservador|Fundos de fundos (FoF) | B9: Conservador | C9: Fundos de fundos (FoF) | D9: 0.2 | F9: Fundos de fundos (FoF)
A10: =B10&"|"&C10 -> Conservador|Híbridos e desenvolvimento | B10: Conservador | C10: Híbridos e desenvolvimento | D10: 0.05 | F10: Híbridos e desenvolvimento
A11: =B11&"|"&C11 -> Moderado|Papel (CRI) | B11: Moderado | C11: Papel (CRI) | D11: 0.3
A12: =B12&"|"&C12 -> Moderado|Logística | B12: Moderado | C12: Logística | D12: 0.25
A13: =B13&"|"&C13 -> Moderado|Shoppings | B13: Moderado | C13: Shoppings | D13: 0.15
A14: =B14&"|"&C14 -> Moderado|Lajes corporativas | B14: Moderado | C14: Lajes corporativas | D14: 0.1
A15: =B15&"|"&C15 -> Moderado|Fundos de fundos (FoF) | B15: Moderado | C15: Fundos de fundos (FoF) | D15: 0.15
A16: =B16&"|"&C16 -> Moderado|Híbridos e desenvolvimento | B16: Moderado | C16: Híbridos e desenvolvimento | D16: 0.05
A17: =B17&"|"&C17 -> Arrojado|Papel (CRI) | B17: Arrojado | C17: Papel (CRI) | D17: 0.15
A18: =B18&"|"&C18 -> Arrojado|Logística | B18: Arrojado | C18: Logística | D18: 0.25
A19: =B19&"|"&C19 -> Arrojado|Shoppings | B19: Arrojado | C19: Shoppings | D19: 0.2
A20: =B20&"|"&C20 -> Arrojado|Lajes corporativas | B20: Arrojado | C20: Lajes corporativas | D20: 0.15
A21: =B21&"|"&C21 -> Arrojado|Fundos de fundos (FoF) | B21: Arrojado | C21: Fundos de fundos (FoF) | D21: 0.1
A22: =B22&"|"&C22 -> Arrojado|Híbridos e desenvolvimento | B22: Arrojado | C22: Híbridos e desenvolvimento | D22: 0.15
